README
josa.py
setup.py
josa.egg-info/PKG-INFO
josa.egg-info/SOURCES.txt
josa.egg-info/dependency_links.txt
josa.egg-info/requires.txt
josa.egg-info/top_level.txt