Metadata-Version: 1.0
Name: josa
Version: 0.0.7
Summary: Appends the correct korean postposition
Home-page: UNKNOWN
Author: Heungsub Lee
Author-email: h@subl.ee
License: BSD
Platform: any
Classifier: Development Status :: 4 - Beta
Classifier: Environment :: Console
Classifier: Intended Audience :: Developers
Classifier: Intended Audience :: Science/Research
Classifier: License :: OSI Approved :: BSD License
Classifier: Natural Language :: Korean
Classifier: Operating System :: OS Independent
Classifier: Programming Language :: Python
Classifier: Topic :: Software Development :: Libraries :: Python Modules
Classifier: Topic :: Text Processing :: Linguistic
